warcio/__init__.py
warcio/archiveiterator.py
warcio/bufferedreaders.py
warcio/capture_http.py
warcio/checker.py
warcio/cli.py
warcio/digestverifyingreader.py
warcio/exceptions.py
warcio/extractor.py
warcio/indexer.py
warcio/limitreader.py
warcio/recompressor.py
warcio/recordbuilder.py
warcio/recordloader.py
warcio/statusandheaders.py
warcio/timeutils.py
warcio/utils.py
warcio/warcwriter.py
warcio-1.7.3.dist-info/LICENSE
warcio-1.7.3.dist-info/METADATA
warcio-1.7.3.dist-info/NOTICE
warcio-1.7.3.dist-info/WHEEL
warcio-1.7.3.dist-info/entry_points.txt
warcio-1.7.3.dist-info/top_level.txt
warcio-1.7.3.dist-info/zip-safe
warcio-1.7.3.dist-info/RECORD
